<Properties StartupConfiguration="{5D854D52-F8E5-45E9-968C-28CABAA6FEA3}|Default">
  <MonoDevelop.Ide.Workbench ActiveDocument="theFallenCity/Load/MainGame/GamePlay.cs">
    <Files>
      <File FileName="theFallenCity/Load/MainGame/Maps/Map1.xml" Line="43" Column="105" />
      <File FileName="theFallenCity/Load/MainGame/GamePlay.cs" Line="15" Column="1" />
      <File FileName="theFallenCity/Load/MainGame/MapAge/Layer.cs" Line="14" Column="5" />
      <File FileName="theFallenCity/Image.cs" Line="25" Column="44" />
      <File FileName="theFallenCity/Load/Menus/MenuManager.cs" Line="17" Column="41" />
    </Files>
  </MonoDevelop.Ide.Workbench>
  <MonoDevelop.Ide.ItemProperties.theFallenCity PreferredExecutionTarget="MonoDevelop.Default" />
  <MonoDevelop.Ide.DebuggingService.PinnedWatches />
  <MonoDevelop.Ide.Workspace ActiveConfiguration="Debug" />
  <MonoDevelop.Ide.DebuggingService.Breakpoints>
    <BreakpointStore />
  </MonoDevelop.Ide.DebuggingService.Breakpoints>
  <MultiItemStartupConfigurations />
</Properties>